setup.cfg
setup.py
pyeosio/__init__.py
pyeosio/action.py
pyeosio/endpoints.py
pyeosio/json_rpc_wrapper.py
pyeosio/suites.py
pyeosio/transaction_builder.py
pyeosio/utils.py
pyeosio.egg-info/PKG-INFO
pyeosio.egg-info/SOURCES.txt
pyeosio.egg-info/dependency_links.txt
pyeosio.egg-info/not-zip-safe
pyeosio.egg-info/requires.txt
pyeosio.egg-info/top_level.txt