Metadata-Version: 1.0
Name: pyeosio
Version: 0.1.1
Summary: EOSIO node connector for Python
Home-page: https://github.com/psy2848048/pyeosio
Author: Junhang (Bryan) RHEE
Author-email: psy2848048@gmail.com
License: MIT
Platform: UNKNOWN
